xaml/CHANGES
xaml/LICENSE
xaml/__init__.py
xaml/__main__.py
xaml/vim/synmenu.vim
xaml/vim/colors/desertleaf.vim
xaml/vim/ftplugin/xaml.vim
xaml/vim/indent/xaml.vim
xaml/vim/syntax/xaml.vim
xaml-0.6.5.dist-info/METADATA
xaml-0.6.5.dist-info/WHEEL
xaml-0.6.5.dist-info/entry_points.txt
xaml-0.6.5.dist-info/top_level.txt
xaml-0.6.5.dist-info/RECORD
